fnllm/__init__.py
fnllm/enums.py
fnllm/errors.py
fnllm/py.typed
fnllm/base/__init__.py
fnllm/base/base_llm.py
fnllm/base/config/__init__.py
fnllm/base/config/config.py
fnllm/base/config/json_strategy.py
fnllm/base/config/retry_strategy.py
fnllm/base/services/__init__.py
fnllm/base/services/cached.py
fnllm/base/services/decorator.py
fnllm/base/services/errors.py
fnllm/base/services/history_extractor.py
fnllm/base/services/json.py
fnllm/base/services/rate_limiter.py
fnllm/base/services/retryer.py
fnllm/base/services/usage_extractor.py
fnllm/base/services/variable_injector.py
fnllm/caching/__init__.py
fnllm/caching/base.py
fnllm/caching/blob.py
fnllm/caching/file.py
fnllm/events/__init__.py
fnllm/events/base.py
fnllm/events/composite.py
fnllm/events/logger.py
fnllm/events/usage_tracker.py
fnllm/limiting/__init__.py
fnllm/limiting/base.py
fnllm/limiting/composite.py
fnllm/limiting/concurrency.py
fnllm/limiting/noop_llm.py
fnllm/limiting/rpm.py
fnllm/limiting/tpm.py
fnllm/limiting/types.py
fnllm/limiting/update_limiter.py
fnllm/openai/__init__.py
fnllm/openai/config.py
fnllm/openai/errors.py
fnllm/openai/roles.py
fnllm/openai/utils.py
fnllm/openai/factories/__init__.py
fnllm/openai/factories/chat.py
fnllm/openai/factories/client.py
fnllm/openai/factories/create_azure_openai_client.py
fnllm/openai/factories/embeddings.py
fnllm/openai/factories/max_retries.py
fnllm/openai/factories/utils.py
fnllm/openai/llm/__init__.py
fnllm/openai/llm/openai_chat_llm.py
fnllm/openai/llm/openai_embeddings_batcher.py
fnllm/openai/llm/openai_embeddings_llm.py
fnllm/openai/llm/openai_streaming_chat_llm.py
fnllm/openai/llm/openai_text_chat_llm.py
fnllm/openai/services/__init__.py
fnllm/openai/services/openai_embeddings_cache_adapter.py
fnllm/openai/services/openai_history_extractor.py
fnllm/openai/services/openai_json.py
fnllm/openai/services/openai_retryable_error_handler.py
fnllm/openai/services/openai_text_chat_cache_adapter.py
fnllm/openai/services/openai_text_service.py
fnllm-0.4.1.dist-info/METADATA
fnllm-0.4.1.dist-info/WHEEL
fnllm-0.4.1.dist-info/licenses/LICENSE
fnllm-0.4.1.dist-info/RECORD
