Metadata-Version: 2.4
Name: fnllm
Version: 0.4.1
Summary: A function-based LLM protocol and wrapper.
Author-email: Chris Trevino <chtrevin@microsoft.com>, Rodrigo Racanicci <rracanicci@microsoft.com>
License:     MIT License
License-File: LICENSE
Requires-Python: >=3.10
Requires-Dist: aiolimiter>=1.1.0
Requires-Dist: httpx>=0.27.0
Requires-Dist: json-repair>=0.30.0
Requires-Dist: pydantic>=2.8.2
Requires-Dist: tenacity>=8.5.0
Provides-Extra: azure
Requires-Dist: azure-identity>=1.17.1; extra == 'azure'
Requires-Dist: azure-storage-blob>=12.20.0; extra == 'azure'
Provides-Extra: numpy
Requires-Dist: numpy>=1.26.4; extra == 'numpy'
Provides-Extra: openai
Requires-Dist: openai>=1.99.9; extra == 'openai'
Requires-Dist: tiktoken>=0.11.0; extra == 'openai'
